file/__init__.py
file/error.py
tests/__init__.py
tests/file/__init__.py
tests/file/test_file.py
retrotv_file-0.0.4a0.dist-info/LICENSE
retrotv_file-0.0.4a0.dist-info/METADATA
retrotv_file-0.0.4a0.dist-info/WHEEL
retrotv_file-0.0.4a0.dist-info/top_level.txt
retrotv_file-0.0.4a0.dist-info/RECORD
