Metadata-Version: 2.1
Name: retrotv-file
Version: 0.0.4a0
Summary: 파일을 편하게 다루기 위한 패키지
Home-page: https://github.com/retrotv-pypi-repo/file
Author: RetroTV
Author-email: yjj8353@gmail.com
Keywords: retrotv,RetroTV,yjj8353,file,File,pypi
Classifier: Programming Language :: Python :: 3
Classifier: Programming Language :: Python :: 3.8
Classifier: Programming Language :: Python :: 3.9
Classifier: Programming Language :: Python :: 3.10
Classifier: Programming Language :: Python :: 3.11
Classifier: Programming Language :: Python :: 3.12
Classifier: Programming Language :: Python :: 3.13
Requires-Python: >=3.8
License-File: LICENSE
